README.txt
setup.cfg
setup.py
repoze/__init__.py
repoze.who_use_beaker.egg-info/PKG-INFO
repoze.who_use_beaker.egg-info/SOURCES.txt
repoze.who_use_beaker.egg-info/dependency_links.txt
repoze.who_use_beaker.egg-info/namespace_packages.txt
repoze.who_use_beaker.egg-info/not-zip-safe
repoze.who_use_beaker.egg-info/requires.txt
repoze.who_use_beaker.egg-info/top_level.txt
repoze/who/__init__.py
repoze/who/plugins/__init__.py
repoze/who/plugins/use_beaker.py