Metadata-Version: 1.0
Name: repoze.who-use-beaker
Version: 0.3
Summary: Identifier plugin for repoze.who with beaker.session cache implementation
Home-page: UNKNOWN
Author: Linas Juskevicius
Author-email: linas@idiles.com
License: MIT
Keywords: beaker session auth repoze.who userid
Platform: UNKNOWN
